typesense/__init__.py
typesense/alias.py
typesense/aliases.py
typesense/analytics.py
typesense/analytics_events.py
typesense/analytics_rule.py
typesense/analytics_rule_v1.py
typesense/analytics_rules.py
typesense/analytics_rules_v1.py
typesense/analytics_v1.py
typesense/api_call.py
typesense/client.py
typesense/collection.py
typesense/collections.py
typesense/configuration.py
typesense/conversation_model.py
typesense/conversations_models.py
typesense/curation_set.py
typesense/curation_sets.py
typesense/debug.py
typesense/document.py
typesense/documents.py
typesense/exceptions.py
typesense/key.py
typesense/keys.py
typesense/logger.py
typesense/metrics.py
typesense/multi_search.py
typesense/nl_search_model.py
typesense/nl_search_models.py
typesense/node_manager.py
typesense/operations.py
typesense/override.py
typesense/overrides.py
typesense/preprocess.py
typesense/py.typed
typesense/request_handler.py
typesense/stemming.py
typesense/stemming_dictionaries.py
typesense/stemming_dictionary.py
typesense/stopwords.py
typesense/stopwords_set.py
typesense/synonym.py
typesense/synonym_set.py
typesense/synonym_sets.py
typesense/synonyms.py
typesense/types/__init__.py
typesense/types/alias.py
typesense/types/analytics.py
typesense/types/analytics_rule_v1.py
typesense/types/collection.py
typesense/types/conversations_model.py
typesense/types/curation_set.py
typesense/types/debug.py
typesense/types/document.py
typesense/types/key.py
typesense/types/multi_search.py
typesense/types/nl_search_model.py
typesense/types/operations.py
typesense/types/override.py
typesense/types/stemming.py
typesense/types/stopword.py
typesense/types/synonym.py
typesense/types/synonym_set.py
typesense-1.3.0.dist-info/licenses/LICENSE
typesense-1.3.0.dist-info/METADATA
typesense-1.3.0.dist-info/WHEEL
typesense-1.3.0.dist-info/top_level.txt
typesense-1.3.0.dist-info/RECORD
